card_identifier/__init__.py
card_identifier/card_issuer.py
card_identifier/card_type.py
card_identifier/cardutils.py
card_identifier-1.0.dist-info/DESCRIPTION.rst
card_identifier-1.0.dist-info/METADATA
card_identifier-1.0.dist-info/RECORD
card_identifier-1.0.dist-info/WHEEL
card_identifier-1.0.dist-info/metadata.json
card_identifier-1.0.dist-info/top_level.txt
